regionconnect/__init__.py
regionconnect/regionconnect.py
regionconnect-0.12.dist-info/LICENSE
regionconnect-0.12.dist-info/METADATA
regionconnect-0.12.dist-info/WHEEL
regionconnect-0.12.dist-info/entry_points.txt
regionconnect-0.12.dist-info/top_level.txt
regionconnect-0.12.dist-info/RECORD
