Metadata-Version: 2.1
Name: regionconnect
Version: 0.12
Summary: IIT Human Brain Atlas regionconnect tool
Home-page: https://github.com/SheridanQ/regionconnect.git
Author: Xiaoxiao Qi
Author-email: xqi10@hawk.iit.edu
License: MIT
Platform: UNKNOWN
Classifier: Development Status :: 3 - Alpha
Classifier: Intended Audience :: Developers
Classifier: Topic :: Software Development :: Build Tools
Requires-Dist: numpy
Requires-Dist: nibabel
